edc.py
eoxhub.py
eoxhub-0.0.2.dist-info/LICENSE
eoxhub-0.0.2.dist-info/METADATA
eoxhub-0.0.2.dist-info/WHEEL
eoxhub-0.0.2.dist-info/top_level.txt
eoxhub-0.0.2.dist-info/RECORD
