Metadata-Version: 2.1
Name: eoxhub
Version: 0.0.2
License-File: LICENSE
Requires-Dist: ipython
Requires-Dist: requests
Requires-Dist: python-dotenv
